amacle_pac/__init__.py
amacle_pac/amacle.py
amacle_package-0.0.1.dist-info/METADATA
amacle_package-0.0.1.dist-info/WHEEL
amacle_package-0.0.1.dist-info/top_level.txt
amacle_package-0.0.1.dist-info/RECORD
